README.md
setup.py
baselines/__init__.py
bdl_benchmarks.egg-info/PKG-INFO
bdl_benchmarks.egg-info/SOURCES.txt
bdl_benchmarks.egg-info/dependency_links.txt
bdl_benchmarks.egg-info/requires.txt
bdl_benchmarks.egg-info/top_level.txt
bdlb/__init__.py
bdlb/core/__init__.py
bdlb/core/benchmark.py
bdlb/core/constants.py
bdlb/core/levels.py
bdlb/core/plotting.py
bdlb/core/registered.py
bdlb/core/transforms.py
bdlb/diabetic_retinopathy_diagnosis/__init__.py
bdlb/diabetic_retinopathy_diagnosis/benchmark.py
bdlb/diabetic_retinopathy_diagnosis/tfds_adapter.py