Metadata-Version: 2.1
Name: bdl-benchmarks
Version: 0.0.1
Summary: BDL Benchmarks
Home-page: https://github.com/oatml/bdl-benchmarks
Author: Oxford Applied and Theoretical Machine Learning Group
Author-email: oatml@googlegroups.com
License: Apache-2.0
Platform: UNKNOWN
Classifier: Development Status :: 3 - Alpha
Classifier: Topic :: Software Development :: Build Tools
Classifier: Programming Language :: Python :: 3.5
Classifier: Programming Language :: Python :: 3.6
Classifier: Programming Language :: Python :: 3.7
